README.md
pileup2sam.py
setup.py
pileup2sam.egg-info/PKG-INFO
pileup2sam.egg-info/SOURCES.txt
pileup2sam.egg-info/dependency_links.txt
pileup2sam.egg-info/entry_points.txt
pileup2sam.egg-info/requires.txt
pileup2sam.egg-info/top_level.txt