Metadata-Version: 2.1
Name: pileup2sam
Version: 0.3.0
Summary: Convert pileup to SAM
Home-page: https://github.com/winni2k/pileup2sam
Author: Warren W. Kretzschmar
Author-email: warren.kretzschmar@ki.se
License: UNKNOWN
Keywords: htslib sam bam pileup samtools
Platform: UNKNOWN
Classifier: Development Status :: 3 - Alpha
Classifier: Intended Audience :: Science/Research
Classifier: License :: OSI Approved :: Apache Software License
Classifier: Programming Language :: Python :: 3.7
Requires-Python: >=3.7, <4
